gada/__init__.py
gada/__main__.py
gada/__version__.py
gada/component.py
gada/datadir.py
gada/main.py
gada/test_utils.py
gada/runners/__init__.py
gada/runners/generic.py
test/__init__.py
test/test_component.py
test/test_main.py
test/test_runners.py
test/utils.py
test/testnodes/__init__.py
gada-0.7a0.dist-info/LICENSE
gada-0.7a0.dist-info/METADATA
gada-0.7a0.dist-info/WHEEL
gada-0.7a0.dist-info/entry_points.txt
gada-0.7a0.dist-info/top_level.txt
gada-0.7a0.dist-info/RECORD
