Metadata-Version: 2.1
Name: gada
Version: 0.7a0
Summary: Python bridge to run code written in any language
Home-page: https://github.com/gadalang/gada
Author: Jeremy Morosi
Author-email: jeremymorosi@hotmail.com
License: UNKNOWN
Project-URL: Bug Tracker, https://github.com/gadalang/gada/issues
Project-URL: Source Code, https://github.com/gadalang/gada/
Platform: UNKNOWN
Classifier: Development Status :: 3 - Alpha
Classifier: Intended Audience :: Developers
Classifier: Topic :: Software Development :: Build Tools
Classifier: Programming Language :: Python :: 3.7
Classifier: Programming Language :: Python :: 3.8
Classifier: Programming Language :: Python :: 3.9
Requires-Python: >=3.7
Requires-Dist: pyyaml
